{"cameraMode":{"drawMode":0,"name":"Shaded","section":"Shading Mode"},"sceneLighting":true,"audioPlay":false,"sceneViewState":{"m_AlwaysRefresh":false,"showFog":true,"showSkybox":true,"showFlares":true,"showImageEffects":true,"showParticleSystems":true,"showVisualEffectGraphs":true,"m_FxEnabled":true},"in2DMode":false,"pivot":{"x":-1.340842843055725,"y":9.17879581451416,"z":-4.32753324508667},"rotation":{"x":-0.3203333020210266,"y":-0.14292557537555695,"z":0.04896458610892296,"w":-0.9352127909660339},"size":4.786895751953125,"orthographic":false}